[{"data":{"tempVal":{"name":"Temperature","unit":"degree celsius","value":"26.1188428744296"},"vibrationVal":{"xaxisVal":{"$numberDecimal":"-1.84824762358571"},"yaxisVal":{"$numberDecimal":"1.90621664373403"},"zaxisVal":{"$numberDecimal":"7.64187978467627"}},"batteryVal":{"name":"battery","value":25},"powerVal":{"name":"power","value":0},"humidityVal":{"name":"Relative Humidity","unit":"%","value":12.0179947494438}},"_id":"621ef72feb090c3f0a8f89dd","timeVal":1645003913586},{"data":{"tempVal":{"name":"Temperature","unit":"degree celsius","value":"24.1559853402403"},"vibrationVal":{"xaxisVal":{"$numberDecimal":"2.43487015698214"},"yaxisVal":{"$numberDecimal":"-0.273899472953451"},"zaxisVal":{"$numberDecimal":"5.82285211648927"}},"batteryVal":{"name":"battery","value":67},"powerVal":{"name":"power","value":53},"humidityVal":{"name":"Relative Humidity","unit":"%","value":68.2400903837546}},"_id":"621ef72feb090c3f0a8f89de","timeVal":1645008633765},{"data":{"tempVal":{"name":"Temperature","unit":"degree celsius","value":"20.2650344385794"},"vibrationVal":{"xaxisVal":{"$numberDecimal":"-3.83459967375631"},"yaxisVal":{"$numberDecimal":"7.75896747527648"},"zaxisVal":{"$numberDecimal":"-0.510188593670168"}},"batteryVal":{"name":"battery","value":50},"powerVal":{"name":"power","value":85},"humidityVal":{"name":"Relative Humidity","unit":"%","value":13.4714694431306}},"_id":"621ef72feb090c3f0a8f89df","timeVal":1645008942682},{"data":{"tempVal":{"name":"Temperature","unit":"degree celsius","value":"26.8787307174336"},"vibrationVal":{"xaxisVal":{"$numberDecimal":"-3.45192766255179"},"yaxisVal":{"$numberDecimal":"-2.58850395532756"},"zaxisVal":{"$numberDecimal":"-1.2502234287078"}},"batteryVal":{"name":"battery","value":25},"powerVal":{"name":"power","value":42},"humidityVal":{"name":"Relative Humidity","unit":"%","value":38.103682692237}},"_id":"621ef72feb090c3f0a8f89e0","timeVal":1645443066320},{"data":{"tempVal":{"name":"Temperature","unit":"degree celsius","value":"24.0271602657075"},"vibrationVal":{"xaxisVal":{"$numberDecimal":"1.46341180768638"},"yaxisVal":{"$numberDecimal":"-0.489343473230328"},"zaxisVal":{"$numberDecimal":"4.19642879357309"}},"batteryVal":{"name":"battery","value":51},"powerVal":{"name":"power","value":18},"humidityVal":{"name":"Relative Humidity","unit":"%","value":68.1128923251673}},"_id":"621ef72feb090c3f0a8f89e1","timeVal":1645443366762},{"data":{"tempVal":{"name":"Temperature","unit":"degree celsius","value":"22.8620948601419"},"vibrationVal":{"xaxisVal":{"$numberDecimal":"6.58822309173249"},"yaxisVal":{"$numberDecimal":"-1.25110064640097"},"zaxisVal":{"$numberDecimal":"6.85547504867816"}},"batteryVal":{"name":"battery","value":19},"powerVal":{"name":"power","value":57},"humidityVal":{"name":"Relative Humidity","unit":"%","value":45.936098092112}},"_id":"621ef72feb090c3f0a8f89e2","timeVal":1645443667184},{"data":{"tempVal":{"name":"Temperature","unit":"degree celsius","value":"25.7656500809209"},"vibrationVal":{"xaxisVal":{"$numberDecimal":"5.76676759125425"},"yaxisVal":{"$numberDecimal":"-3.31409691757838"},"zaxisVal":{"$numberDecimal":"-2.08899389950492"}},"batteryVal":{"name":"battery","value":40},"powerVal":{"name":"power","value":12},"humidityVal":{"name":"Relative Humidity","unit":"%","value":79.3884908909996}},"_id":"621ef72feb090c3f0a8f89e3","timeVal":1645443967985},{"data":{"tempVal":{"name":"Temperature","unit":"degree celsius","value":"21.4883515433747"},"vibrationVal":{"xaxisVal":{"$numberDecimal":"-2.17895516085417"},"yaxisVal":{"$numberDecimal":"1.80690431656203"},"zaxisVal":{"$numberDecimal":"0.0276525068466702"}},"batteryVal":{"name":"battery","value":31},"powerVal":{"name":"power","value":65},"humidityVal":{"name":"Relative Humidity","unit":"%","value":47.4412510849607}},"_id":"621ef72feb090c3f0a8f89e4","timeVal":1645445838057},{"data":{"tempVal":{"name":"Temperature","unit":"degree celsius","value":"24.7932057077036"},"vibrationVal":{"xaxisVal":{"$numberDecimal":"1.70924921979476"},"yaxisVal":{"$numberDecimal":"0.841929952278257"},"zaxisVal":{"$numberDecimal":"8.20852924395055"}},"batteryVal":{"name":"battery","value":5},"powerVal":{"name":"power","value":17},"humidityVal":{"name":"Relative Humidity","unit":"%","value":15.6372396765844}},"_id":"621ef72feb090c3f0a8f89e5","timeVal":1645446138409},{"data":{"tempVal":{"name":"Temperature","unit":"degree celsius","value":"27.0512422766113"},"vibrationVal":{"xaxisVal":{"$numberDecimal":"2.40611685471346"},"yaxisVal":{"$numberDecimal":"-4.26556432079072"},"zaxisVal":{"$numberDecimal":"8.63488856298833"}},"batteryVal":{"name":"battery","value":50},"powerVal":{"name":"power","value":20},"humidityVal":{"name":"Relative Humidity","unit":"%","value":42.682598903836}},"_id":"621ef72feb090c3f0a8f89e6","timeVal":1645446438696},{"data":{"tempVal":{"name":"Temperature","unit":"degree celsius","value":"21.5429710444809"},"vibrationVal":{"xaxisVal":{"$numberDecimal":"5.98068513801048"},"yaxisVal":{"$numberDecimal":"5.91756105875185"},"zaxisVal":{"$numberDecimal":"2.78187428122662"}},"batteryVal":{"name":"battery","value":67},"powerVal":{"name":"power","value":43},"humidityVal":{"name":"Relative Humidity","unit":"%","value":56.5919666381163}},"_id":"621ef72feb090c3f0a8f89e7","timeVal":1645455000474},{"data":{"tempVal":{"name":"Temperature","unit":"degree celsius","value":"24.1288609445926"},"vibrationVal":{"xaxisVal":{"$numberDecimal":"3.26988937009578"},"yaxisVal":{"$numberDecimal":"-4.67160958124039"},"zaxisVal":{"$numberDecimal":"7.70966049503195"}},"batteryVal":{"name":"battery","value":56},"powerVal":{"name":"power","value":17},"humidityVal":{"name":"Relative Humidity","unit":"%","value":58.9713192358721}},"_id":"621ef72feb090c3f0a8f89e8","timeVal":1645455304376},{"data":{"tempVal":{"name":"Temperature","unit":"degree celsius","value":"29.418164155608"},"vibrationVal":{"xaxisVal":{"$numberDecimal":"2.23801247729678"},"yaxisVal":{"$numberDecimal":"1.95735236783572"},"zaxisVal":{"$numberDecimal":"2.36707587147763"}},"batteryVal":{"name":"battery","value":27},"powerVal":{"name":"power","value":57},"humidityVal":{"name":"Relative Humidity","unit":"%","value":44.9588485708711}},"_id":"621ef72feb090c3f0a8f89e9","timeVal":1645456267903},{"data":{"tempVal":{"name":"Temperature","unit":"degree celsius","value":"21.9711995248211"},"vibrationVal":{"xaxisVal":{"$numberDecimal":"7.16512977863493"},"yaxisVal":{"$numberDecimal":"-0.00499582090969675"},"zaxisVal":{"$numberDecimal":"2.6932533406357"}},"batteryVal":{"name":"battery","value":29},"powerVal":{"name":"power","value":79},"humidityVal":{"name":"Relative Humidity","unit":"%","value":33.9818121249539}},"_id":"621ef72feb090c3f0a8f89ea","timeVal":1645456590849},{"data":{"tempVal":{"name":"Temperature","unit":"degree celsius","value":"25.9203212428041"},"vibrationVal":{"xaxisVal":{"$numberDecimal":"2.27721518225093"},"yaxisVal":{"$numberDecimal":"4.75986750334525"},"zaxisVal":{"$numberDecimal":"-3.1245637314714"}},"batteryVal":{"name":"battery","value":53},"powerVal":{"name":"power","value":63},"humidityVal":{"name":"Relative Humidity","unit":"%","value":34.2359916785752}},"_id":"621ef72feb090c3f0a8f89eb","timeVal":1645457016719},{"data":{"tempVal":{"name":"Temperature","unit":"degree celsius","value":"26.2182503079799"},"vibrationVal":{"xaxisVal":{"$numberDecimal":"-0.766861768880852"},"yaxisVal":{"$numberDecimal":"7.99058060617803"},"zaxisVal":{"$numberDecimal":"5.12649993423501"}},"batteryVal":{"name":"battery","value":68},"powerVal":{"name":"power","value":94},"humidityVal":{"name":"Relative Humidity","unit":"%","value":57.1576882565932}},"_id":"621ef72feb090c3f0a8f89ec","timeVal":1645457317579},{"data":{"tempVal":{"name":"Temperature","unit":"degree celsius","value":"20.6530936546738"},"vibrationVal":{"xaxisVal":{"$numberDecimal":"-4.946669887024"},"yaxisVal":{"$numberDecimal":"-4.9650806806018"},"zaxisVal":{"$numberDecimal":"8.80186245768035"}},"batteryVal":{"name":"battery","value":15},"powerVal":{"name":"power","value":23},"humidityVal":{"name":"Relative Humidity","unit":"%","value":30.7982030611989}},"_id":"621ef72feb090c3f0a8f89ed","timeVal":1645457618286},{"data":{"tempVal":{"name":"Temperature","unit":"degree celsius","value":"24.9898486690655"},"vibrationVal":{"xaxisVal":{"$numberDecimal":"0.148756575579725"},"yaxisVal":{"$numberDecimal":"6.67276245842626"},"zaxisVal":{"$numberDecimal":"5.4467949855323"}},"batteryVal":{"name":"battery","value":35},"powerVal":{"name":"power","value":11},"humidityVal":{"name":"Relative Humidity","unit":"%","value":42.7960961070253}},"_id":"621ef72feb090c3f0a8f89ee","timeVal":1645457918457},{"data":{"tempVal":{"name":"Temperature","unit":"degree celsius","value":"26.4961731874064"},"vibrationVal":{"xaxisVal":{"$numberDecimal":"-1.33798339090377"},"yaxisVal":{"$numberDecimal":"3.96494232338748"},"zaxisVal":{"$numberDecimal":"0.822726665945098"}},"batteryVal":{"name":"battery","value":49},"powerVal":{"name":"power","value":58},"humidityVal":{"name":"Relative Humidity","unit":"%","value":46.9647367739629}},"_id":"621ef72feb090c3f0a8f89ef","timeVal":1645458218820},{"data":{"tempVal":{"name":"Temperature","unit":"degree celsius","value":"22.0723518022577"},"vibrationVal":{"xaxisVal":{"$numberDecimal":"-2.111267123457"},"yaxisVal":{"$numberDecimal":"4.65247643672019"},"zaxisVal":{"$numberDecimal":"3.66219226836783"}},"batteryVal":{"name":"battery","value":9},"powerVal":{"name":"power","value":73},"humidityVal":{"name":"Relative Humidity","unit":"%","value":47.1795452256359}},"_id":"621ef72feb090c3f0a8f89f0","timeVal":1645458520144},{"data":{"tempVal":{"name":"Temperature","unit":"degree celsius","value":"21.3742689661865"},"vibrationVal":{"xaxisVal":{"$numberDecimal":"0.790905673048688"},"yaxisVal":{"$numberDecimal":"6.79625471469639"},"zaxisVal":{"$numberDecimal":"-4.05692327102855"}},"batteryVal":{"name":"battery","value":82},"powerVal":{"name":"power","value":1},"humidityVal":{"name":"Relative Humidity","unit":"%","value":39.7188288840914}},"_id":"621ef72feb090c3f0a8f89f1","timeVal":1645458820354},{"data":{"tempVal":{"name":"Temperature","unit":"degree celsius","value":"22.1429978708077"},"vibrationVal":{"xaxisVal":{"$numberDecimal":"4.71855625100195"},"yaxisVal":{"$numberDecimal":"-0.382137433572272"},"zaxisVal":{"$numberDecimal":"-2.31995324590995"}},"batteryVal":{"name":"battery","value":95},"powerVal":{"name":"power","value":72},"humidityVal":{"name":"Relative Humidity","unit":"%","value":12.1173190369825}},"_id":"621ef72feb090c3f0a8f89f2","timeVal":1645459123375},{"data":{"tempVal":{"name":"Temperature","unit":"degree celsius","value":"29.1867630598121"},"vibrationVal":{"xaxisVal":{"$numberDecimal":"1.39221319365492"},"yaxisVal":{"$numberDecimal":"-1.70585145133951"},"zaxisVal":{"$numberDecimal":"8.83829901726155"}},"batteryVal":{"name":"battery","value":88},"powerVal":{"name":"power","value":54},"humidityVal":{"name":"Relative Humidity","unit":"%","value":23.4067007521151}},"_id":"621ef72feb090c3f0a8f89f3","timeVal":1645459423858},{"data":{"tempVal":{"name":"Temperature","unit":"degree celsius","value":"22.4261202853865"},"vibrationVal":{"xaxisVal":{"$numberDecimal":"-0.28737049654106"},"yaxisVal":{"$numberDecimal":"4.13394234698727"},"zaxisVal":{"$numberDecimal":"2.11444264434545"}},"batteryVal":{"name":"battery","value":98},"powerVal":{"name":"power","value":81},"humidityVal":{"name":"Relative Humidity","unit":"%","value":10.4611602756875}},"_id":"621ef72feb090c3f0a8f89f4","timeVal":1645459725367},{"data":{"tempVal":{"name":"Temperature","unit":"degree celsius","value":"25.9335223685447"},"vibrationVal":{"xaxisVal":{"$numberDecimal":"9.78455975549894"},"yaxisVal":{"$numberDecimal":"-2.1336507267927"},"zaxisVal":{"$numberDecimal":"7.50928658363888"}},"batteryVal":{"name":"battery","value":27},"powerVal":{"name":"power","value":79},"humidityVal":{"name":"Relative Humidity","unit":"%","value":44.5974612110306}},"_id":"621ef72feb090c3f0a8f89f5","timeVal":1645460074721},{"data":{"tempVal":{"name":"Temperature","unit":"degree celsius","value":"25.8001056978261"},"vibrationVal":{"xaxisVal":{"$numberDecimal":"-1.51393842435211"},"yaxisVal":{"$numberDecimal":"-0.251499119339665"},"zaxisVal":{"$numberDecimal":"-0.931428341835566"}},"batteryVal":{"name":"battery","value":90},"powerVal":{"name":"power","value":47},"humidityVal":{"name":"Relative Humidity","unit":"%","value":27.5809261761506}},"_id":"621ef72feb090c3f0a8f89f6","timeVal":1645460375919},{"data":{"tempVal":{"name":"Temperature","unit":"degree celsius","value":"24.9089499570132"},"vibrationVal":{"xaxisVal":{"$numberDecimal":"8.47419041532326"},"yaxisVal":{"$numberDecimal":"1.76209100906424"},"zaxisVal":{"$numberDecimal":"1.34225662769467"}},"batteryVal":{"name":"battery","value":40},"powerVal":{"name":"power","value":5},"humidityVal":{"name":"Relative Humidity","unit":"%","value":77.6753685446585}},"_id":"621ef72feb090c3f0a8f89f7","timeVal":1645460676115},{"data":{"tempVal":{"name":"Temperature","unit":"degree celsius","value":"21.1766193244138"},"vibrationVal":{"xaxisVal":{"$numberDecimal":"3.47460838856394"},"yaxisVal":{"$numberDecimal":"-3.36446489582059"},"zaxisVal":{"$numberDecimal":"4.27644327123078"}},"batteryVal":{"name":"battery","value":27},"powerVal":{"name":"power","value":17},"humidityVal":{"name":"Relative Humidity","unit":"%","value":13.6689190877039}},"_id":"621ef72feb090c3f0a8f89f8","timeVal":1645460976585},{"data":{"tempVal":{"name":"Temperature","unit":"degree celsius","value":"20.5760194800091"},"vibrationVal":{"xaxisVal":{"$numberDecimal":"2.59675402052375"},"yaxisVal":{"$numberDecimal":"9.16807394236414"},"zaxisVal":{"$numberDecimal":"3.34894059753822"}},"batteryVal":{"name":"battery","value":14},"powerVal":{"name":"power","value":73},"humidityVal":{"name":"Relative Humidity","unit":"%","value":30.2950545732904}},"_id":"621ef72feb090c3f0a8f89f9","timeVal":1645461276748},{"data":{"tempVal":{"name":"Temperature","unit":"degree celsius","value":"27.357252483285"},"vibrationVal":{"xaxisVal":{"$numberDecimal":"9.88790684690342"},"yaxisVal":{"$numberDecimal":"6.70831897707286"},"zaxisVal":{"$numberDecimal":"6.68814241008823"}},"batteryVal":{"name":"battery","value":82},"powerVal":{"name":"power","value":16},"humidityVal":{"name":"Relative Humidity","unit":"%","value":59.5805186269548}},"_id":"621ef72feb090c3f0a8f89fa","timeVal":1645461578240},{"data":{"tempVal":{"name":"Temperature","unit":"degree celsius","value":"21.2762757516644"},"vibrationVal":{"xaxisVal":{"$numberDecimal":"1.8707034395677"},"yaxisVal":{"$numberDecimal":"5.99274799352106"},"zaxisVal":{"$numberDecimal":"0.0266288623048094"}},"batteryVal":{"name":"battery","value":7},"powerVal":{"name":"power","value":37},"humidityVal":{"name":"Relative Humidity","unit":"%","value":49.0881191830622}},"_id":"621ef72feb090c3f0a8f89fb","timeVal":1645461882964},{"data":{"tempVal":{"name":"Temperature","unit":"degree celsius","value":"20.7799351474634"},"vibrationVal":{"xaxisVal":{"$numberDecimal":"7.90669316662858"},"yaxisVal":{"$numberDecimal":"8.00385930326441"},"zaxisVal":{"$numberDecimal":"-1.5106405726588"}},"batteryVal":{"name":"battery","value":76},"powerVal":{"name":"power","value":45},"humidityVal":{"name":"Relative Humidity","unit":"%","value":25.2864198648869}},"_id":"621ef72feb090c3f0a8f89fc","timeVal":1645462184452},{"data":{"tempVal":{"name":"Temperature","unit":"degree celsius","value":"26.7845760585686"},"vibrationVal":{"xaxisVal":{"$numberDecimal":"2.66374778703265"},"yaxisVal":{"$numberDecimal":"2.16126148883741"},"zaxisVal":{"$numberDecimal":"9.5584440267825"}},"batteryVal":{"name":"battery","value":12},"powerVal":{"name":"power","value":94},"humidityVal":{"name":"Relative Humidity","unit":"%","value":30.0146847404427}},"_id":"621ef72feb090c3f0a8f89fd","timeVal":1645462484625},{"data":{"tempVal":{"name":"Temperature","unit":"degree celsius","value":"20.5073971879882"},"vibrationVal":{"xaxisVal":{"$numberDecimal":"3.09615122248716"},"yaxisVal":{"$numberDecimal":"6.16379804247725"},"zaxisVal":{"$numberDecimal":"-4.07053011843181"}},"batteryVal":{"name":"battery","value":34},"powerVal":{"name":"power","value":47},"humidityVal":{"name":"Relative Humidity","unit":"%","value":39.4351276262673}},"_id":"621ef72feb090c3f0a8f89fe","timeVal":1645462785260},{"data":{"tempVal":{"name":"Temperature","unit":"degree celsius","value":"25.2667067687013"},"vibrationVal":{"xaxisVal":{"$numberDecimal":"5.3763556707945"},"yaxisVal":{"$numberDecimal":"-2.7490901015788"},"zaxisVal":{"$numberDecimal":"-3.19561087258089"}},"batteryVal":{"name":"battery","value":12},"powerVal":{"name":"power","value":66},"humidityVal":{"name":"Relative Humidity","unit":"%","value":52.1537401799168}},"_id":"621ef72feb090c3f0a8f89ff","timeVal":1645463086294},{"data":{"tempVal":{"name":"Temperature","unit":"degree celsius","value":"28.3007899599952"},"vibrationVal":{"xaxisVal":{"$numberDecimal":"3.00427092288172"},"yaxisVal":{"$numberDecimal":"-2.62764646479982"},"zaxisVal":{"$numberDecimal":"8.68856302561615"}},"batteryVal":{"name":"battery","value":32},"powerVal":{"name":"power","value":67},"humidityVal":{"name":"Relative Humidity","unit":"%","value":71.6563149219846}},"_id":"621ef72feb090c3f0a8f8a00","timeVal":1645463387051},{"data":{"tempVal":{"name":"Temperature","unit":"degree celsius","value":"25.5070652712891"},"vibrationVal":{"xaxisVal":{"$numberDecimal":"7.21309209484821"},"yaxisVal":{"$numberDecimal":"6.40969769976298"},"zaxisVal":{"$numberDecimal":"7.18702411165031"}},"batteryVal":{"name":"battery","value":3},"powerVal":{"name":"power","value":83},"humidityVal":{"name":"Relative Humidity","unit":"%","value":44.8887088641965}},"_id":"621ef72feb090c3f0a8f8a01","timeVal":1645463688165},{"data":{"tempVal":{"name":"Temperature","unit":"degree celsius","value":"29.3141254073144"},"vibrationVal":{"xaxisVal":{"$numberDecimal":"2.99970287221624"},"yaxisVal":{"$numberDecimal":"-1.44129914364403"},"zaxisVal":{"$numberDecimal":"3.04027470261903"}},"batteryVal":{"name":"battery","value":96},"powerVal":{"name":"power","value":25},"humidityVal":{"name":"Relative Humidity","unit":"%","value":44.7924278208351}},"_id":"621ef72feb090c3f0a8f8a02","timeVal":1645463989158},{"data":{"tempVal":{"name":"Temperature","unit":"degree celsius","value":"27.4588789640422"},"vibrationVal":{"xaxisVal":{"$numberDecimal":"-1.34978175774258"},"yaxisVal":{"$numberDecimal":"4.61758595384838"},"zaxisVal":{"$numberDecimal":"1.62577674363799"}},"batteryVal":{"name":"battery","value":18},"powerVal":{"name":"power","value":99},"humidityVal":{"name":"Relative Humidity","unit":"%","value":44.8963634773158}},"_id":"621ef72feb090c3f0a8f8a03","timeVal":1645464289233},{"data":{"tempVal":{"name":"Temperature","unit":"degree celsius","value":"27.8547215369148"},"vibrationVal":{"xaxisVal":{"$numberDecimal":"2.46830286839612"},"yaxisVal":{"$numberDecimal":"-0.0954445317183623"},"zaxisVal":{"$numberDecimal":"6.16597814241186"}},"batteryVal":{"name":"battery","value":42},"powerVal":{"name":"power","value":25},"humidityVal":{"name":"Relative Humidity","unit":"%","value":17.5200508022854}},"_id":"621ef72feb090c3f0a8f8a04","timeVal":1645464589389},{"data":{"tempVal":{"name":"Temperature","unit":"degree celsius","value":"24.0675892893489"},"vibrationVal":{"xaxisVal":{"$numberDecimal":"2.12781306170526"},"yaxisVal":{"$numberDecimal":"-3.12209839261286"},"zaxisVal":{"$numberDecimal":"6.31353902214799"}},"batteryVal":{"name":"battery","value":30},"powerVal":{"name":"power","value":98},"humidityVal":{"name":"Relative Humidity","unit":"%","value":74.4996358587784}},"_id":"621ef72feb090c3f0a8f8a05","timeVal":1645464889706},{"data":{"tempVal":{"name":"Temperature","unit":"degree celsius","value":"28.6266144733952"},"vibrationVal":{"xaxisVal":{"$numberDecimal":"-1.37412435684436"},"yaxisVal":{"$numberDecimal":"-2.99106591503684"},"zaxisVal":{"$numberDecimal":"-1.97326450607067"}},"batteryVal":{"name":"battery","value":62},"powerVal":{"name":"power","value":24},"humidityVal":{"name":"Relative Humidity","unit":"%","value":28.001370488405}},"_id":"621ef72feb090c3f0a8f8a06","timeVal":1645465189871},{"data":{"tempVal":{"name":"Temperature","unit":"degree celsius","value":"22.2571425621948"},"vibrationVal":{"xaxisVal":{"$numberDecimal":"6.11625870154162"},"yaxisVal":{"$numberDecimal":"-4.02651665243147"},"zaxisVal":{"$numberDecimal":"9.92092727367773"}},"batteryVal":{"name":"battery","value":29},"powerVal":{"name":"power","value":8},"humidityVal":{"name":"Relative Humidity","unit":"%","value":77.1566650293108}},"_id":"621ef72feb090c3f0a8f8a07","timeVal":1645465490300},{"data":{"tempVal":{"name":"Temperature","unit":"degree celsius","value":"27.9692397925683"},"vibrationVal":{"xaxisVal":{"$numberDecimal":"5.06022405360222"},"yaxisVal":{"$numberDecimal":"3.1527680314531"},"zaxisVal":{"$numberDecimal":"0.00624202577640531"}},"batteryVal":{"name":"battery","value":34},"powerVal":{"name":"power","value":45},"humidityVal":{"name":"Relative Humidity","unit":"%","value":42.5418560933518}},"_id":"621ef72feb090c3f0a8f8a08","timeVal":1645465791290},{"data":{"tempVal":{"name":"Temperature","unit":"degree celsius","value":"29.2789251641986"},"vibrationVal":{"xaxisVal":{"$numberDecimal":"8.87398721452106"},"yaxisVal":{"$numberDecimal":"4.77108231629682"},"zaxisVal":{"$numberDecimal":"0.863700831036085"}},"batteryVal":{"name":"battery","value":58},"powerVal":{"name":"power","value":70},"humidityVal":{"name":"Relative Humidity","unit":"%","value":10.8547884129224}},"_id":"621ef72feb090c3f0a8f8a09","timeVal":1645466092242},{"data":{"tempVal":{"name":"Temperature","unit":"degree celsius","value":"20.9575823598482"},"vibrationVal":{"xaxisVal":{"$numberDecimal":"4.5306857191782"},"yaxisVal":{"$numberDecimal":"2.01659740305496"},"zaxisVal":{"$numberDecimal":"-1.44942239700616"}},"batteryVal":{"name":"battery","value":41},"powerVal":{"name":"power","value":60},"humidityVal":{"name":"Relative Humidity","unit":"%","value":43.2452174490583}},"_id":"621ef72feb090c3f0a8f8a0a","timeVal":1645466393326},{"data":{"tempVal":{"name":"Temperature","unit":"degree celsius","value":"26.183736533624"},"vibrationVal":{"xaxisVal":{"$numberDecimal":"9.70045651998248"},"yaxisVal":{"$numberDecimal":"-1.94292445702783"},"zaxisVal":{"$numberDecimal":"4.18427226907652"}},"batteryVal":{"name":"battery","value":24},"powerVal":{"name":"power","value":7},"humidityVal":{"name":"Relative Humidity","unit":"%","value":27.5877174306845}},"_id":"621ef72feb090c3f0a8f8a0b","timeVal":1645466694439},{"data":{"tempVal":{"name":"Temperature","unit":"degree celsius","value":"20.2331167138198"},"vibrationVal":{"xaxisVal":{"$numberDecimal":"-2.95060951757282"},"yaxisVal":{"$numberDecimal":"-2.00266708285502"},"zaxisVal":{"$numberDecimal":"8.97555887247024"}},"batteryVal":{"name":"battery","value":87},"powerVal":{"name":"power","value":53},"humidityVal":{"name":"Relative Humidity","unit":"%","value":18.4715170211078}},"_id":"621ef72feb090c3f0a8f8a0c","timeVal":1645466994461},{"data":{"tempVal":{"name":"Temperature","unit":"degree celsius","value":"22.3546124895881"},"vibrationVal":{"xaxisVal":{"$numberDecimal":"-1.18985246939961"},"yaxisVal":{"$numberDecimal":"8.18509077637062"},"zaxisVal":{"$numberDecimal":"9.7137034343143"}},"batteryVal":{"name":"battery","value":95},"powerVal":{"name":"power","value":3},"humidityVal":{"name":"Relative Humidity","unit":"%","value":50.0976561673644}},"_id":"621ef72feb090c3f0a8f8a0d","timeVal":1645467295233},{"data":{"tempVal":{"name":"Temperature","unit":"degree celsius","value":"29.6913820551667"},"vibrationVal":{"xaxisVal":{"$numberDecimal":"5.93535486309131"},"yaxisVal":{"$numberDecimal":"9.57125547677597"},"zaxisVal":{"$numberDecimal":"7.31565695344139"}},"batteryVal":{"name":"battery","value":75},"powerVal":{"name":"power","value":84},"humidityVal":{"name":"Relative Humidity","unit":"%","value":74.849548871263}},"_id":"621ef72feb090c3f0a8f8a0e","timeVal":1645467595439},{"data":{"tempVal":{"name":"Temperature","unit":"degree celsius","value":"24.4543703424386"},"vibrationVal":{"xaxisVal":{"$numberDecimal":"-3.21126238510654"},"yaxisVal":{"$numberDecimal":"-3.16606820579877"},"zaxisVal":{"$numberDecimal":"2.25352193696126"}},"batteryVal":{"name":"battery","value":69},"powerVal":{"name":"power","value":58},"humidityVal":{"name":"Relative Humidity","unit":"%","value":79.8379242547098}},"_id":"621ef72feb090c3f0a8f8a0f","timeVal":1645467895879},{"data":{"tempVal":{"name":"Temperature","unit":"degree celsius","value":"26.9107895039629"},"vibrationVal":{"xaxisVal":{"$numberDecimal":"7.28677857106095"},"yaxisVal":{"$numberDecimal":"-0.606635707880628"},"zaxisVal":{"$numberDecimal":"8.74160488466955"}},"batteryVal":{"name":"battery","value":57},"powerVal":{"name":"power","value":46},"humidityVal":{"name":"Relative Humidity","unit":"%","value":77.956085005613}},"_id":"621ef72feb090c3f0a8f8a10","timeVal":1645468196042},{"data":{"tempVal":{"name":"Temperature","unit":"degree celsius","value":"26.394121071951"},"vibrationVal":{"xaxisVal":{"$numberDecimal":"-2.19855404370573"},"yaxisVal":{"$numberDecimal":"4.53136764767781"},"zaxisVal":{"$numberDecimal":"3.44321152301269"}},"batteryVal":{"name":"battery","value":92},"powerVal":{"name":"power","value":86},"humidityVal":{"name":"Relative Humidity","unit":"%","value":57.3159377537495}},"_id":"621ef72feb090c3f0a8f8a11","timeVal":1645468497248},{"data":{"tempVal":{"name":"Temperature","unit":"degree celsius","value":"20.8726738478408"},"vibrationVal":{"xaxisVal":{"$numberDecimal":"5.4897174204272"},"yaxisVal":{"$numberDecimal":"3.14461299794519"},"zaxisVal":{"$numberDecimal":"1.32340668649857"}},"batteryVal":{"name":"battery","value":76},"powerVal":{"name":"power","value":16},"humidityVal":{"name":"Relative Humidity","unit":"%","value":49.2338895748063}},"_id":"621ef72feb090c3f0a8f8a12","timeVal":1645468797480},{"data":{"tempVal":{"name":"Temperature","unit":"degree celsius","value":"24.6692406472519"},"vibrationVal":{"xaxisVal":{"$numberDecimal":"8.1498788262094"},"yaxisVal":{"$numberDecimal":"9.76971931453377"},"zaxisVal":{"$numberDecimal":"6.69794653433932"}},"batteryVal":{"name":"battery","value":11},"powerVal":{"name":"power","value":71},"humidityVal":{"name":"Relative Humidity","unit":"%","value":56.1040082397606}},"_id":"621ef72feb090c3f0a8f8a13","timeVal":1645469100153},{"data":{"tempVal":{"name":"Temperature","unit":"degree celsius","value":"29.6512538195585"},"vibrationVal":{"xaxisVal":{"$numberDecimal":"1.85705911895227"},"yaxisVal":{"$numberDecimal":"9.42734909647892"},"zaxisVal":{"$numberDecimal":"8.0712545395063"}},"batteryVal":{"name":"battery","value":84},"powerVal":{"name":"power","value":59},"humidityVal":{"name":"Relative Humidity","unit":"%","value":72.3459295895088}},"_id":"621ef72feb090c3f0a8f8a14","timeVal":1645469400299},{"data":{"tempVal":{"name":"Temperature","unit":"degree celsius","value":"28.2982624219925"},"vibrationVal":{"xaxisVal":{"$numberDecimal":"-2.59175893935881"},"yaxisVal":{"$numberDecimal":"-4.43544888279633"},"zaxisVal":{"$numberDecimal":"-1.82300909530144"}},"batteryVal":{"name":"battery","value":91},"powerVal":{"name":"power","value":98},"humidityVal":{"name":"Relative Humidity","unit":"%","value":79.6138076804908}},"_id":"621ef72feb090c3f0a8f8a15","timeVal":1645469701122},{"data":{"tempVal":{"name":"Temperature","unit":"degree celsius","value":"20.0763430844023"},"vibrationVal":{"xaxisVal":{"$numberDecimal":"4.50664305410943"},"yaxisVal":{"$numberDecimal":"0.0592263839158154"},"zaxisVal":{"$numberDecimal":"5.02855844272455"}},"batteryVal":{"name":"battery","value":72},"powerVal":{"name":"power","value":15},"humidityVal":{"name":"Relative Humidity","unit":"%","value":45.6747905148649}},"_id":"621ef72feb090c3f0a8f8a16","timeVal":1645470001127},{"data":{"tempVal":{"name":"Temperature","unit":"degree celsius","value":"29.1291239815851"},"vibrationVal":{"xaxisVal":{"$numberDecimal":"3.28940848362206"},"yaxisVal":{"$numberDecimal":"8.01529239321991"},"zaxisVal":{"$numberDecimal":"6.38175827501522"}},"batteryVal":{"name":"battery","value":44},"powerVal":{"name":"power","value":61},"humidityVal":{"name":"Relative Humidity","unit":"%","value":35.2604824624217}},"_id":"621ef72feb090c3f0a8f8a17","timeVal":1645470301779},{"data":{"tempVal":{"name":"Temperature","unit":"degree celsius","value":"20.9203580234605"},"vibrationVal":{"xaxisVal":{"$numberDecimal":"2.02834634710399"},"yaxisVal":{"$numberDecimal":"2.33127521088946"},"zaxisVal":{"$numberDecimal":"-3.69354943290615"}},"batteryVal":{"name":"battery","value":81},"powerVal":{"name":"power","value":29},"humidityVal":{"name":"Relative Humidity","unit":"%","value":29.8661172720559}},"_id":"621ef72feb090c3f0a8f8a18","timeVal":1645470602468},{"data":{"tempVal":{"name":"Temperature","unit":"degree celsius","value":"24.4131849047337"},"vibrationVal":{"xaxisVal":{"$numberDecimal":"1.83450297837524"},"yaxisVal":{"$numberDecimal":"-4.95990382936264"},"zaxisVal":{"$numberDecimal":"8.16877111353219"}},"batteryVal":{"name":"battery","value":30},"powerVal":{"name":"power","value":24},"humidityVal":{"name":"Relative Humidity","unit":"%","value":15.308194538595}},"_id":"621ef72feb090c3f0a8f8a19","timeVal":1645470902834},{"data":{"tempVal":{"name":"Temperature","unit":"degree celsius","value":"24.2931788118535"},"vibrationVal":{"xaxisVal":{"$numberDecimal":"8.70448337595901"},"yaxisVal":{"$numberDecimal":"5.81052766658761"},"zaxisVal":{"$numberDecimal":"-4.25978297431336"}},"batteryVal":{"name":"battery","value":43},"powerVal":{"name":"power","value":14},"humidityVal":{"name":"Relative Humidity","unit":"%","value":15.3580962364364}},"_id":"621ef72feb090c3f0a8f8a1a","timeVal":1645471202925},{"data":{"tempVal":{"name":"Temperature","unit":"degree celsius","value":"26.9505088543486"},"vibrationVal":{"xaxisVal":{"$numberDecimal":"2.29081665720341"},"yaxisVal":{"$numberDecimal":"2.15031142654073"},"zaxisVal":{"$numberDecimal":"-4.22654740046333"}},"batteryVal":{"name":"battery","value":36},"powerVal":{"name":"power","value":98},"humidityVal":{"name":"Relative Humidity","unit":"%","value":79.8979610516843}},"_id":"621ef72feb090c3f0a8f8a1b","timeVal":1645471503580},{"data":{"tempVal":{"name":"Temperature","unit":"degree celsius","value":"28.8439899906154"},"vibrationVal":{"xaxisVal":{"$numberDecimal":"3.29006969905511"},"yaxisVal":{"$numberDecimal":"6.39264144002105"},"zaxisVal":{"$numberDecimal":"-2.44231988189165"}},"batteryVal":{"name":"battery","value":15},"powerVal":{"name":"power","value":77},"humidityVal":{"name":"Relative Humidity","unit":"%","value":49.626415533747}},"_id":"621ef72feb090c3f0a8f8a1c","timeVal":1645471804060},{"data":{"tempVal":{"name":"Temperature","unit":"degree celsius","value":"23.1140532727796"},"vibrationVal":{"xaxisVal":{"$numberDecimal":"3.50838036380573"},"yaxisVal":{"$numberDecimal":"7.54852660267769"},"zaxisVal":{"$numberDecimal":"5.25634689317912"}},"batteryVal":{"name":"battery","value":58},"powerVal":{"name":"power","value":31},"humidityVal":{"name":"Relative Humidity","unit":"%","value":76.3551759274497}},"_id":"621ef72feb090c3f0a8f8a1d","timeVal":1645472105087},{"data":{"tempVal":{"name":"Temperature","unit":"degree celsius","value":"26.1190469703146"},"vibrationVal":{"xaxisVal":{"$numberDecimal":"-0.206576591395614"},"yaxisVal":{"$numberDecimal":"5.18694328588188"},"zaxisVal":{"$numberDecimal":"-2.80018296823095"}},"batteryVal":{"name":"battery","value":21},"powerVal":{"name":"power","value":94},"humidityVal":{"name":"Relative Humidity","unit":"%","value":37.5392364503503}},"_id":"621ef72feb090c3f0a8f8a1e","timeVal":1645472406132},{"data":{"tempVal":{"name":"Temperature","unit":"degree celsius","value":"20.9059796098757"},"vibrationVal":{"xaxisVal":{"$numberDecimal":"7.83076989899895"},"yaxisVal":{"$numberDecimal":"7.54824164041503"},"zaxisVal":{"$numberDecimal":"0.960373422726061"}},"batteryVal":{"name":"battery","value":75},"powerVal":{"name":"power","value":93},"humidityVal":{"name":"Relative Humidity","unit":"%","value":33.0369547752501}},"_id":"621ef72feb090c3f0a8f8a1f","timeVal":1645472706712},{"data":{"tempVal":{"name":"Temperature","unit":"degree celsius","value":"26.9655727486306"},"vibrationVal":{"xaxisVal":{"$numberDecimal":"5.48624254444228"},"yaxisVal":{"$numberDecimal":"1.39922321487163"},"zaxisVal":{"$numberDecimal":"5.89332949946188"}},"batteryVal":{"name":"battery","value":2},"powerVal":{"name":"power","value":81},"humidityVal":{"name":"Relative Humidity","unit":"%","value":71.0253525367159}},"_id":"621ef72feb090c3f0a8f8a20","timeVal":1645473007502}]